strool/__init__.py
strool/strool.py
strool-1.0.1.dist-info/METADATA
strool-1.0.1.dist-info/WHEEL
strool-1.0.1.dist-info/licenses/LICENSE
strool-1.0.1.dist-info/RECORD
