Metadata-Version: 2.3
Name: strool
Version: 1.0.1
Summary: Small module to control strings with booleans
Project-URL: Homepage, https://github.com/1emank/strool
Project-URL: Issues, https://github.com/1emank/strool/issues
Author-email: Carlos González <carlos.a.gb95@gmail.com>
License-File: LICENSE
Classifier: License :: OSI Approved :: MIT License
Classifier: Operating System :: OS Independent
Classifier: Programming Language :: Python :: 3
Requires-Python: >=3.10
